{
  "kind": "collectionType",
  "collectionName": "oganic_patterns",
  "info": {
    "name": "OganicPatterns"
  },
  "options": {
    "increments": true,
    "timestamps": true
  },
  "attributes": {
    "image": {
      "model": "file",
      "via": "related",
      "allowedTypes": [
        "images",
        "files",
        "videos"
      ],
      "plugin": "upload",
      "required": false
    },
    "door": {
      "model": "file",
      "via": "related",
      "allowedTypes": [
        "images",
        "files",
        "videos"
      ],
      "plugin": "upload",
      "required": false
    },
    "description": {
      "type": "string"
    }
  }
}
